[
    {
        "title" : " This is Title",
        "shortDesc" : "this is a short description 1",
        "fullDesc" : "this is a full description"
    },

     {
        "title" : "This is Title",
        "shortDesc" : "this is a short description 1",
        "fullDesc" : "this is a full description"
    },

     {
        "title" : "Title",
        "shortDesc" : "this is a short description 1",
        "fullDesc" : "this is a full description"
    },

     {
        "title" : "Title",
        "shortDesc" : "this is a short description 1",
        "fullDesc" : "this is a full description"
    },

     {
        "title" : "Title",
        "shortDesc" : "this is a short description 1",
        "fullDesc" : "this is a full description"
    }
]